cratedb_mcp/__init__.py
cratedb_mcp/__main__.py
cratedb_mcp/cli.py
cratedb_mcp/core.py
cratedb_mcp/knowledge.py
cratedb_mcp/settings.py
cratedb_mcp/tool.py
cratedb_mcp/prompt/__init__.py
cratedb_mcp/prompt/instructions.md
cratedb_mcp/util/__init__.py
cratedb_mcp/util/sql.py
cratedb_mcp-0.0.9.dist-info/licenses/LICENSE
cratedb_mcp-0.0.9.dist-info/METADATA
cratedb_mcp-0.0.9.dist-info/WHEEL
cratedb_mcp-0.0.9.dist-info/entry_points.txt
cratedb_mcp-0.0.9.dist-info/top_level.txt
cratedb_mcp-0.0.9.dist-info/RECORD
