Metadata-Version: 2.4
Name: cratedb-mcp
Version: 0.0.9
Summary: CrateDB MCP Server for natural-language Text-to-SQL and documentation retrieval.
Author: CrateDB engineering
License-Expression: Apache-2.0
Keywords: cratedb,documentation retrieval,knowledge base,mcp,mcp server,model context protocol,sql,text-to-sql
Classifier: Development Status :: 4 - Beta
Classifier: Environment :: Console
Classifier: Intended Audience :: Customer Service
Classifier: Intended Audience :: Developers
Classifier: Intended Audience :: Education
Classifier: Intended Audience :: End Users/Desktop
Classifier: Intended Audience :: Information Technology
Classifier: Intended Audience :: Manufacturing
Classifier: Intended Audience :: Science/Research
Classifier: Intended Audience :: System Administrators
Classifier: Intended Audience :: Telecommunications Industry
Classifier: Operating System :: MacOS :: MacOS X
Classifier: Operating System :: Microsoft :: Windows
Classifier: Operating System :: POSIX :: Linux
Classifier: Operating System :: Unix
Classifier: Programming Language :: Python
Classifier: Programming Language :: Python :: 3 :: Only
Classifier: Programming Language :: Python :: 3.10
Classifier: Programming Language :: Python :: 3.11
Classifier: Programming Language :: Python :: 3.12
Classifier: Programming Language :: Python :: 3.13
Classifier: Programming Language :: Python :: 3.14
Classifier: Topic :: Adaptive Technologies
Classifier: Topic :: Communications
Classifier: Topic :: Database
Classifier: Topic :: Documentation
Classifier: Topic :: Education
Classifier: Topic :: Internet
Classifier: Topic :: Office/Business
Classifier: Topic :: Scientific/Engineering
Classifier: Topic :: Software Development :: Libraries
Classifier: Topic :: Software Development :: Pre-processors
Classifier: Topic :: System :: Clustering
Classifier: Topic :: System :: Distributed Computing
Classifier: Topic :: System :: Logging
Classifier: Topic :: System :: Monitoring
Classifier: Topic :: System :: Networking
Classifier: Topic :: System :: Systems Administration
Classifier: Topic :: Text Processing
Classifier: Topic :: Utilities
Requires-Python: >=3.10
License-File: LICENSE
Requires-Dist: attrs
Requires-Dist: cachetools<7
Requires-Dist: click<9
Requires-Dist: cratedb-about<0.1.0
Requires-Dist: fastmcp<2.14,>=2.13
Requires-Dist: hishel<0.2
Requires-Dist: pueblo==0.0.11
Requires-Dist: sqlparse<0.6
Provides-Extra: develop
Requires-Dist: mypy<1.19; extra == "develop"
Requires-Dist: poethepoet<1; extra == "develop"
Requires-Dist: pyproject-fmt<3; extra == "develop"
Requires-Dist: ruff<0.15; extra == "develop"
Requires-Dist: validate-pyproject<1; extra == "develop"
Provides-Extra: docs
Requires-Dist: furo; extra == "docs"
Requires-Dist: myst-parser[linkify]<5,>=0.18; extra == "docs"
Requires-Dist: sphinx-autobuild==2021.3.14; extra == "docs"
Requires-Dist: sphinx-copybutton; extra == "docs"
Requires-Dist: sphinx-design-elements<1; extra == "docs"
Requires-Dist: sphinxcontrib-mermaid<2; extra == "docs"
Requires-Dist: sphinxext-opengraph<1; extra == "docs"
Provides-Extra: test
Requires-Dist: pytest<9; extra == "test"
Requires-Dist: pytest-cov<8; extra == "test"
Requires-Dist: pytest-mock<4; extra == "test"
Dynamic: license-file
